parq/__init__.py
parq-0.3.0.dist-info/LICENSE
parq-0.3.0.dist-info/METADATA
parq-0.3.0.dist-info/WHEEL
parq-0.3.0.dist-info/top_level.txt
parq-0.3.0.dist-info/zip-safe
parq-0.3.0.dist-info/RECORD
