Metadata-Version: 2.1
Name: parq
Version: 0.3.0
Summary: A multi-process job queue
Author-email: Rob Moss <rgmoss@unimelb.edu.au>
Maintainer-email: Rob Moss <rgmoss@unimelb.edu.au>
License: Copyright (c) 2016-2023, Rob Moss
Project-URL: homepage, https://bitbucket.org/robmoss/job-queue/
Project-URL: repository, https://bitbucket.org/robmoss/job-queue/
Project-URL: documentation, https://parq.readthedocs.io/en/latest/
Project-URL: changelog, https://parq.readthedocs.io/en/latest/changelog.html
Classifier: Development Status :: 4 - Beta
Classifier: Intended Audience :: Science/Research
Classifier: License :: OSI Approved :: BSD License
Classifier: Operating System :: OS Independent
Classifier: Programming Language :: Python
Classifier: Programming Language :: Python :: 3
Classifier: Topic :: Scientific/Engineering :: Mathematics
Requires-Python: >=3.8
License-File: LICENSE
Provides-Extra: tests
Requires-Dist: pytest ; extra == 'tests'
Requires-Dist: pytest-cov (~=4.0) ; extra == 'tests'
